pyfabdb/__init__.py
pyfabdb/client.py
pyfabdb/pyfabdb.py
pyfabdb/util.py
pyfabdb-0.1.0.dist-info/LICENSE
pyfabdb-0.1.0.dist-info/METADATA
pyfabdb-0.1.0.dist-info/WHEEL
pyfabdb-0.1.0.dist-info/top_level.txt
pyfabdb-0.1.0.dist-info/RECORD
