Metadata-Version: 2.1
Name: pyfabdb
Version: 0.1.0
Summary: A Python Library for Flesh and Blood DB API
Home-page: https://github.com/GonzalezAndrew/pyfabdb
Author: Andrew Gonzalez
Author-email: andrewgonzo23@gmail.com
License: MIT
Platform: UNKNOWN
Classifier: License :: OSI Approved :: MIT License
Classifier: Programming Language :: Python :: 3
Classifier: Programming Language :: Python :: 3 :: Only
Classifier: Programming Language :: Python :: 3.6
Classifier: Programming Language :: Python :: 3.7
Classifier: Programming Language :: Python :: 3.8
Classifier: Programming Language :: Python :: 3.9
Classifier: Programming Language :: Python :: Implementation :: CPython
Requires-Python: >=3.6.1
License-File: LICENSE
Requires-Dist: certifi (==2021.5.30)
Requires-Dist: charset-normalizer (==2.0.4)
Requires-Dist: idna (==3.2)
Requires-Dist: requests (==2.26.0)
Requires-Dist: urllib3 (==1.26.6)
